MANIFEST.in
README.md
README.rst
lshift.py
setup.py
lshift.egg-info/PKG-INFO
lshift.egg-info/SOURCES.txt
lshift.egg-info/dependency_links.txt
lshift.egg-info/top_level.txt