Metadata-Version: 1.1
Name: lshift
Version: 0.1.1
Summary: left shift args to make a function a partial application
Home-page: https://github.com/v2e4lisp/lshift
Author: Yan Wenjun
Author-email: mylastnameisyan@gmail.com
License: MIT
Platform: UNKNOWN
Classifier: License :: OSI Approved :: MIT License
Classifier: Topic :: Software Development :: Libraries
